MANIFEST.in
setup.cfg
setup.py
CoilMQ.egg-info/PKG-INFO
CoilMQ.egg-info/SOURCES.txt
CoilMQ.egg-info/dependency_links.txt
CoilMQ.egg-info/entry_points.txt
CoilMQ.egg-info/not-zip-safe
CoilMQ.egg-info/requires.txt
CoilMQ.egg-info/top_level.txt
coilmq/__init__.py
coilmq/engine.py
coilmq/exception.py
coilmq/queue.py
coilmq/scheduler.py
coilmq/start.py
coilmq/topic.py
coilmq/auth/__init__.py
coilmq/auth/simple.py
coilmq/config/__init__.py
coilmq/config/coilmq.cfg-sample
coilmq/config/defaults.cfg
coilmq/protocol/__init__.py
coilmq/server/__init__.py
coilmq/server/socket_server.py
coilmq/store/__init__.py
coilmq/store/dbm.py
coilmq/store/memory.py
coilmq/store/rds.py
coilmq/store/sa/__init__.py
coilmq/store/sa/meta.py
coilmq/store/sa/model.py
coilmq/util/__init__.py
coilmq/util/concurrency.py
coilmq/util/frames.py
docs/news.txt
requirements/build.txt
requirements/prod.txt
requirements/test.txt