Metadata-Version: 1.1
Name: CoilMQ
Version: 1.0.0
Summary: 
